.coveragerc
CHANGELOG.txt
CONTRIBUTORS.txt
LICENSE.txt
MANIFEST.in
README.txt
ez_setup.py
setup.cfg
setup.py
test.cfg
TurboGears.egg-info/PKG-INFO
TurboGears.egg-info/SOURCES.txt
TurboGears.egg-info/dependency_links.txt
TurboGears.egg-info/entry_points.txt
TurboGears.egg-info/not-zip-safe
TurboGears.egg-info/requires.txt
TurboGears.egg-info/top_level.txt
doc/README.txt
doc/build_api_docs.sh
doc/doc.ini
tools/codename.py
tools/test_all_quickstarts.py
tools/tgsetup.py
tools/toolbox-start.py
turbogears/__init__.py
turbogears/config.py
turbogears/controllers.py
turbogears/database.py
turbogears/decorator.py
turbogears/docgen.py
turbogears/errorhandling.py
turbogears/finddata.py
turbogears/paginate.py
turbogears/release.py
turbogears/scheduler.py
turbogears/startup.py
turbogears/testutil.py
turbogears/util.py
turbogears/validators.py
turbogears/command/__init__.py
turbogears/command/base.py
turbogears/command/i18n.py
turbogears/command/info.py
turbogears/command/kid2genshi.py
turbogears/command/quickstart.py
turbogears/command/sacommand.py
turbogears/feed/__init__.py
turbogears/feed/atom0_3.kid
turbogears/feed/atom1_0.kid
turbogears/feed/feed.py
turbogears/feed/rss2_0.kid
turbogears/filters/__init__.py
turbogears/filters/base.py
turbogears/filters/safemultipart.py
turbogears/i18n/__init__.py
turbogears/i18n/format.py
turbogears/i18n/kidutils.py
turbogears/i18n/tg_gettext.py
turbogears/i18n/utils.py
turbogears/i18n/data/TurboGears.pot
turbogears/i18n/data/__init__.py
turbogears/i18n/data/af.py
turbogears/i18n/data/af_ZA.py
turbogears/i18n/data/am.py
turbogears/i18n/data/am_ET.py
turbogears/i18n/data/ar.py
turbogears/i18n/data/ar_AE.py
turbogears/i18n/data/ar_BH.py
turbogears/i18n/data/ar_DZ.py
turbogears/i18n/data/ar_EG.py
turbogears/i18n/data/ar_IN.py
turbogears/i18n/data/ar_IQ.py
turbogears/i18n/data/ar_JO.py
turbogears/i18n/data/ar_KW.py
turbogears/i18n/data/ar_LB.py
turbogears/i18n/data/ar_LY.py
turbogears/i18n/data/ar_MA.py
turbogears/i18n/data/ar_OM.py
turbogears/i18n/data/ar_QA.py
turbogears/i18n/data/ar_SA.py
turbogears/i18n/data/ar_SD.py
turbogears/i18n/data/ar_SY.py
turbogears/i18n/data/ar_TN.py
turbogears/i18n/data/ar_YE.py
turbogears/i18n/data/be.py
turbogears/i18n/data/be_BY.py
turbogears/qstemplates/qsbase/+einame+.egg-info/PKG-INFO
turbogears/qstemplates/qsbase/+einame+.egg-info/sqlobject.txt_tmpl
