Metadata-Version: 1.0
Name: TurboGears
Version: 1.1.3
Summary: Front-to-back, open-source, rapid web development framework
Home-page: http://www.turbogears.org/
Author: TurboGears Release Team
Author-email: turbogears@googlegroups.com
License: MIT
Download-URL: http://www.turbogears.org/1.1/downloads/1.1.3/index
Platform: UNKNOWN
Classifier: Development Status :: 5 - Production/Stable
Classifier: Environment :: Console
Classifier: Framework :: TurboGears
Classifier: Intended Audience :: Developers
Classifier: License :: OSI Approved :: MIT License
Classifier: Operating System :: OS Independent
Classifier: Programming Language :: Python
Classifier: Programming Language :: Python :: 2.4
Classifier: Programming Language :: Python :: 2.5
Classifier: Programming Language :: Python :: 2.6
Classifier: Topic :: Internet :: WWW/HTTP
Classifier: Topic :: Software Development :: Libraries :: Python Modules
